rememory/__init__.py
rememory/namedLock.py
rememory/sharedBlock.py
rememory/sharedBool.py
rememory/sharedDict.py
rememory/sharedFloat.py
rememory/sharedInt.py
rememory/sharedList.py
rememory/sharedString.py
rememory-0.3.4.dist-info/licenses/LICENSE
testScript/__init__.py
testScript/exception.py
testScript/worker_file.py
rememory-0.3.4.dist-info/METADATA
rememory-0.3.4.dist-info/WHEEL
rememory-0.3.4.dist-info/entry_points.txt
rememory-0.3.4.dist-info/top_level.txt
rememory-0.3.4.dist-info/RECORD
