Metadata-Version: 2.4
Name: rememory
Version: 0.3.4
Summary: A set of lightweight shared memory variable types for safe multiprocessing access
Author: Nichola Walch
Author-email: Nichola Walch <littler.compression@gmail.com>
License: MIT
Requires-Python: >=3.8
License-File: LICENSE
Requires-Dist: pywin32>=305; sys_platform == "win32"
Requires-Dist: posix-ipc>=1.2.0; sys_platform != "win32"
Dynamic: author
Dynamic: license-file
Dynamic: requires-python
